README.md
setup.py
tests/__init__.py
tests/integration/__init__.py
tests/integration/test_basic_app.py
tests/mixins/__init__.py
tests/mixins/async_mixin.py
tests/unit/__init__.py
tests/unit/test_app.py
tests/unit/test_route_manager.py
tests/unit/middleware/__init__.py
tests/unit/middleware/test_builtin.py
vortex/__init__.py
vortex/app.py
vortex/errors.py
vortex/logger.py
vortex/routes.py
vortex/threading_utils.py
vortex/typing.py
vortex/middlewares/__init__.py
vortex/middlewares/builtin.py
vortex/middlewares/errors.py
vortex/middlewares/headers.py
vortex/middlewares/logger.py
vortex/serialization/__init__.py
vortex/serialization/json_serializer.py
vortex_http.egg-info/PKG-INFO
vortex_http.egg-info/SOURCES.txt
vortex_http.egg-info/dependency_links.txt
vortex_http.egg-info/requires.txt
vortex_http.egg-info/top_level.txt